docs/conf.py
skullTo3d/__init__.py
skullTo3d/_version.py
skullTo3d/nodes/__init__.py
skullTo3d/nodes/noise.py
skullTo3d/nodes/skull.py
skullTo3d/nodes/tests/test_skull.py
skullTo3d/pipelines/__init__.py
skullTo3d/pipelines/angio_pipe.py
skullTo3d/pipelines/rename.py
skullTo3d/pipelines/skull_pipe.py
skullTo3d/pipelines/tests/test_skull_pipe.py
skullTo3d/utils/utils_params.py
skullto3d-0.1.dist-info/licenses/LICENSE
workflows/__init__.py
workflows/params_segment_macaque_0p5_ants_4animal_skull.json
workflows/params_segment_macaque_0p5_ants_4animal_skullnoisypetra.json
workflows/params_segment_macaque_0p5_ants_quick_skull.json
workflows/params_segment_macaque_0p5_ants_quick_skullnoisypetra.json
workflows/params_segment_macaque_0p5_ants_skull.json
workflows/params_segment_macaque_0p5_ants_skullnoisypetra.json
workflows/params_segment_macaque_ants_4animal_skull.json
workflows/params_segment_macaque_ants_4animal_skullnoisypetra.json
workflows/params_segment_macaque_ants_quick_skull.json
workflows/params_segment_macaque_ants_quick_skullnoisypetra.json
workflows/params_segment_macaque_ants_skull.json
workflows/params_segment_macaque_ants_skullnoisypetra.json
workflows/params_segment_macaque_skull.json
workflows/params_segment_macaque_spm_skull.json
workflows/params_segment_macaque_spm_skullnoisypetra.json
workflows/params_segment_marmo_ants_4animal_skull.json
workflows/params_segment_marmo_ants_quick_skull.json
workflows/params_segment_marmo_ants_skull.json
workflows/params_segment_marmo_spm_skull.json
workflows/params_segment_marmot2_ants_skull.json
workflows/params_segment_marmot2_spm_skull.json
workflows/segment_skull.py
skullto3d-0.1.dist-info/METADATA
skullto3d-0.1.dist-info/WHEEL
skullto3d-0.1.dist-info/entry_points.txt
skullto3d-0.1.dist-info/top_level.txt
skullto3d-0.1.dist-info/RECORD
