Metadata-Version: 2.4
Name: skullTo3d
Version: 0.1
Summary: Pipeline for skull extraction for macaque/marmoset 
Author: Macatools team
Maintainer: SkullTo3d developers
License: BSD-3-Clause
Requires-Python: >=3.10
License-File: LICENSE
Requires-Dist: macapype
Requires-Dist: matplotlib
Provides-Extra: doc-deps
Requires-Dist: sphinx; extra == "doc-deps"
Requires-Dist: sphinx-gallery; extra == "doc-deps"
Requires-Dist: sphinx_bootstrap_theme; extra == "doc-deps"
Requires-Dist: numpydoc; extra == "doc-deps"
Requires-Dist: sphinxcontrib-fulltoc; extra == "doc-deps"
Provides-Extra: test-deps
Requires-Dist: pytest; extra == "test-deps"
Requires-Dist: pytest-cov; extra == "test-deps"
Requires-Dist: codecov; extra == "test-deps"
Provides-Extra: flake-deps
Requires-Dist: flake8; extra == "flake-deps"
Provides-Extra: test
Requires-Dist: skullTo3d[flake_deps,test_deps]; extra == "test"
Provides-Extra: doc
Requires-Dist: skullTo3d[doc_deps,flake_deps,test_deps]; extra == "doc"
Dynamic: license-file
